tsproto/__init__.py
tsproto/models.py
tsproto/plots.py
tsproto/utils.py
tsproto/windowshap.py
tsproto-0.3.0.dist-info/LICENSE
tsproto-0.3.0.dist-info/METADATA
tsproto-0.3.0.dist-info/WHEEL
tsproto-0.3.0.dist-info/top_level.txt
tsproto-0.3.0.dist-info/RECORD
