Metadata-Version: 2.1
Name: tsproto
Version: 0.3.0
Summary: Post-host prototype-based explanations with rules for time-series classifiers
Author-email: Szymon Bobek <szymon.bobek@gmail.com>
License: MIT License
Project-URL: Homepage, https://github.com/sbobek/tsproto
Project-URL: Documentation, https://tsproto.readthedocs.org
Project-URL: Issues, https://github.com/sbobek/tsproto/issues
Keywords: xai,time-series,explainability,model-agnostic,rule-based
Classifier: License :: OSI Approved :: MIT License
Classifier: Programming Language :: Python
Classifier: Programming Language :: Python :: 3
Requires-Python: >=3.8
License-File: LICENSE
Requires-Dist: pandas>=1.4.3
Requires-Dist: numpy<2.0,>=1.22.4
Requires-Dist: scikit-learn>=1.1.1
Requires-Dist: matplotlib>=3.5.2
Requires-Dist: matplotlib-inline>=0.1.3
Requires-Dist: seaborn>=0.11.2
Requires-Dist: graphviz>=0.20
Requires-Dist: shap>=0.41.0
Requires-Dist: ruptures>=1.1.8
Requires-Dist: tslearn>=0.6.1
Requires-Dist: kshape>=1.0.6
Requires-Dist: sktime>=0.29.0
Requires-Dist: scikit-learn-extra>=0.3.0
Provides-Extra: gpu
Requires-Dist: torch>=2.0.1; extra == "gpu"
